snaper/__init__.py
snaper/snap.js
jn_snapaa-1.0.14.dist-info/METADATA
jn_snapaa-1.0.14.dist-info/WHEEL
jn_snapaa-1.0.14.dist-info/top_level.txt
jn_snapaa-1.0.14.dist-info/RECORD
