Metadata-Version: 2.1
Name: jn-snapaa
Version: 1.0.14
Summary: a easy snap js
Home-page: https://zhuanlan.zhihu.com/p/26159930
Author: jnddd
Author-email: 122296743@qq.com
License: UNKNOWN
Platform: UNKNOWN
